<?xml version="1.0" encoding="utf-8" ?><dwsync><file name=".htaccess" local="-4469449895723401216" remote="-4469449892502185832" testing="0" /><file name=".roles" local="-4469449895723401216" remote="-4469449892502185832" testing="0" /><file name="access.cnf" local="-4469449895723401216" remote="-4469449892502185832" testing="0" /><file name="botinfs.cnf" local="-4469449895723401216" remote="-4469449892502185832" testing="0" /><file name="bots.cnf" local="-4469449895723401216" remote="-4469449892502185832" testing="0" /><file name="deptodoc.btr" local="-4469449895723401216" remote="-4469449892502185832" testing="0" /><file name="doctodep.btr" local="-4469449895723401216" remote="-4469449892502185832" testing="0" /><file name="linkinfo.btr" local="-4469449895723401216" remote="-4469449892502185832" testing="0" /><file name="service.cnf" local="-4469449895723401216" remote="-4469449892502185832" testing="0" /><file name="service.grp" local="-4469449895723401216" remote="-4469449892502185832" testing="0" /><file name="service.pwd" local="-4469449895723401216" remote="-4469449892502185832" testing="0" /><file name="services.cnf" local="-4469449895723401216" remote="-4469449892502185832" testing="0" /><file name="svcacl.cnf" local="-4469449895723401216" remote="-4469449892502185832" testing="0" /><file name="writeto.cnf" local="-4469449895723401216" remote="-4469449892502185832" testing="0" /></dwsync>